<annotation>
	<folder>images</folder>
	<filename>00065.jpg</filename>
	<path>/home/iokunev/projects/grains/datasets/images/00065.jpg</path>
	<source>
		<database>Unknown</database>
	</source>
	<size>
		<width>823</width>
		<height>1168</height>
		<depth>3</depth>
	</size>
	<segmented>0</segmented>
	<object>
		<name>grains</name>
		<pose>Unspecified</pose>
		<truncated>0</truncated>
		<difficult>0</difficult>
		<bndbox>
			<xmin>559</xmin>
			<ymin>508</ymin>
			<xmax>588</xmax>
			<ymax>543</ymax>
		</bndbox>
	</object>
	<object>
		<name>grains</name>
		<pose>Unspecified</pose>
		<truncated>0</truncated>
		<difficult>0</difficult>
		<bndbox>
			<xmin>523</xmin>
			<ymin>537</ymin>
			<xmax>555</xmax>
			<ymax>576</ymax>
		</bndbox>
	</object>
</annotation>
