<annotation>
	<folder>images</folder>
	<filename>0054.jpg</filename>
	<path>/home/iokunev/projects/grains/datasets/images/0054.jpg</path>
	<source>
		<database>Unknown</database>
	</source>
	<size>
		<width>2471</width>
		<height>3504</height>
		<depth>3</depth>
	</size>
	<segmented>0</segmented>
	<object>
		<name>grains_2mm</name>
		<pose>Unspecified</pose>
		<truncated>0</truncated>
		<difficult>0</difficult>
		<bndbox>
			<xmin>1085</xmin>
			<ymin>890</ymin>
			<xmax>1209</xmax>
			<ymax>1010</ymax>
		</bndbox>
	</object>
	<object>
		<name>grains_2mm</name>
		<pose>Unspecified</pose>
		<truncated>0</truncated>
		<difficult>0</difficult>
		<bndbox>
			<xmin>1635</xmin>
			<ymin>1032</ymin>
			<xmax>1759</xmax>
			<ymax>1152</ymax>
		</bndbox>
	</object>
	<object>
		<name>grains_2mm</name>
		<pose>Unspecified</pose>
		<truncated>0</truncated>
		<difficult>0</difficult>
		<bndbox>
			<xmin>1373</xmin>
			<ymin>1250</ymin>
			<xmax>1497</xmax>
			<ymax>1370</ymax>
		</bndbox>
	</object>
</annotation>
