<annotation>
	<folder>images</folder>
	<filename>0177.jpg</filename>
	<path>/home/iokunev/projects/grains_Mask_RCNN/datasets/images/0177.jpg</path>
	<source>
		<database>Unknown</database>
	</source>
	<size>
		<width>823</width>
		<height>1168</height>
		<depth>3</depth>
	</size>
	<segmented>0</segmented>
	<object>
		<name>grains</name>
		<pose>Unspecified</pose>
		<truncated>0</truncated>
		<difficult>0</difficult>
		<bndbox>
			<xmin>406</xmin>
			<ymin>473</ymin>
			<xmax>448</xmax>
			<ymax>531</ymax>
		</bndbox>
	</object>
</annotation>
